dfac/__init__.py
dfac/__main__.py
dfac/app/Error.py
dfac/app/Help.py
dfac/app/Shell.py
dfac/app/__init__.py
dfac/app/help.txt
dfac/core/ArrayGenerator.py
dfac/core/StringGenerator.py
dfac/core/__init__.py
dfac/generators/ClassicGenerator.py
dfac/generators/__init__.py
dfac/inout/Display.py
dfac/inout/FileGenerator.py
dfac/inout/FileInjestor.py
dfac/inout/__init__.py
dfac/misc/help.txt
dfac/misc/docs/intro.txt
dfac/utilities/Alphanumerics.py
dfac/utilities/__init__.py
dfac-1.0.4.dist-info/METADATA
dfac-1.0.4.dist-info/WHEEL
dfac-1.0.4.dist-info/entry_points.txt
dfac-1.0.4.dist-info/licenses/LICENSE
dfac-1.0.4.dist-info/RECORD
