Metadata-Version: 2.1
Name: dfac
Version: 1.0.4
Summary: A simple to use python app for generating data of different types and configurations.
Project-URL: Homepage, https://github.com/sheunl/Data-Factory
Project-URL: Bug Tracker, https://github.com/sheunl/Data-Factory/issues
Author-email: Abdulrasaq Lawani <me@zaqlabs.com>
License-File: LICENSE
Classifier: License :: OSI Approved :: MIT License
Classifier: Operating System :: OS Independent
Classifier: Programming Language :: Python :: 3
Requires-Python: >=3.10
